{
  "version": 1,
  "activeIssue": "038-wave-2-additive-features-rtk-compressors",
  "workflow": "feature",
  "phase": "implement",
  "phaseHistory": [
    {
      "from": "brainstorm",
      "to": "spec",
      "timestamp": 1772508306318
    },
    {
      "from": "spec",
      "to": "plan",
      "timestamp": 1772508354110
    },
    {
      "from": "plan",
      "to": "implement",
      "timestamp": 1772508463835
    }
  ],
  "reviewApproved": false,
  "planMode": null,
  "planIteration": 1,
  "currentTaskIndex": 0,
  "completedTasks": [],
  "tddTaskState": null,
  "doneActions": [],
  "megaEnabled": true,
  "branchName": null,
  "baseBranch": null
}
