{
  "version": 1,
  "activeIssue": "016-m4-bash-output-compression-filter-routin",
  "workflow": "feature",
  "phase": "implement",
  "phaseHistory": [
    {
      "from": "brainstorm",
      "to": "spec",
      "timestamp": 1772314163697
    },
    {
      "from": "spec",
      "to": "plan",
      "timestamp": 1772314347932
    },
    {
      "from": "plan",
      "to": "review",
      "timestamp": 1772314582529
    },
    {
      "from": "review",
      "to": "plan",
      "timestamp": 1772315408843
    },
    {
      "from": "plan",
      "to": "review",
      "timestamp": 1772316100453
    },
    {
      "from": "review",
      "to": "implement",
      "timestamp": 1772316106922
    },
    {
      "from": "review",
      "to": "plan",
      "timestamp": 1772316480577
    },
    {
      "from": "plan",
      "to": "review",
      "timestamp": 1772317269317
    },
    {
      "from": "review",
      "to": "plan",
      "timestamp": 1772317494102
    },
    {
      "from": "plan",
      "to": "review",
      "timestamp": 1772317775073
    },
    {
      "from": "review",
      "to": "plan",
      "timestamp": 1772317942934
    },
    {
      "from": "plan",
      "to": "review",
      "timestamp": 1772318575565
    },
    {
      "from": "review",
      "to": "plan",
      "timestamp": 1772318843157
    },
    {
      "from": "plan",
      "to": "review",
      "timestamp": 1772333916148
    },
    {
      "from": "review",
      "to": "plan",
      "timestamp": 1772334289443
    },
    {
      "from": "plan",
      "to": "review",
      "timestamp": 1772369743698
    },
    {
      "from": "review",
      "to": "plan",
      "timestamp": 1772370514604
    },
    {
      "from": "plan",
      "to": "review",
      "timestamp": 1772373290936
    },
    {
      "from": "review",
      "to": "plan",
      "timestamp": 1772374282338
    },
    {
      "from": "plan",
      "to": "review",
      "timestamp": 1772377859092
    },
    {
      "from": "review",
      "to": "plan",
      "timestamp": 1772378833073
    },
    {
      "from": "plan",
      "to": "review",
      "timestamp": 1772380677498
    },
    {
      "from": "review",
      "to": "implement",
      "timestamp": 1772380684545
    }
  ],
  "reviewApproved": true,
  "currentTaskIndex": 0,
  "completedTasks": [],
  "tddTaskState": null,
  "taskJJChanges": {},
  "jjChangeId": "kkrppqrm",
  "rootChangeId": null,
  "doneActions": [],
  "megaEnabled": true
}
